sigmamu-0.4.dist-info/licenses/LICENSE
simu/__init__.py
simu/_version.py
simu/py.typed
simu/app/__init__.py
simu/app/data/__init__.py
simu/app/data/parameters.yml
simu/app/data/species.yml
simu/app/data/structures.yml
simu/app/models/__init__.py
simu/app/thermo/__init__.py
simu/app/thermo/factories.py
simu/app/thermo/source.py
simu/app/thermo/state.py
simu/app/thermo/contributions/__init__.py
simu/app/thermo/contributions/basic.py
simu/app/thermo/contributions/special.py
simu/app/thermo/contributions/cubic/__init__.py
simu/app/thermo/contributions/cubic/rk.py
simu/app/thermo/materials/__init__.py
simu/core/__init__.py
simu/core/data/__init__.py
simu/core/data/atomic_weights.yml
simu/core/data/uom_definitions.txt
simu/core/model/__init__.py
simu/core/model/amodel.py
simu/core/model/base.py
simu/core/model/bound.py
simu/core/model/hierarchy.py
simu/core/model/material.py
simu/core/model/numeric.py
simu/core/model/parameter.py
simu/core/model/property.py
simu/core/solver/__init__.py
simu/core/solver/simulation.py
simu/core/thermo/__init__.py
simu/core/thermo/contribution.py
simu/core/thermo/factory.py
simu/core/thermo/frame.py
simu/core/thermo/material.py
simu/core/thermo/parameters.py
simu/core/thermo/species.py
simu/core/thermo/state.py
simu/core/utilities/__init__.py
simu/core/utilities/configurable.py
simu/core/utilities/constants.py
simu/core/utilities/errors.py
simu/core/utilities/molecules.py
simu/core/utilities/output.py
simu/core/utilities/qstructures.py
simu/core/utilities/quantity.py
simu/core/utilities/residual.py
simu/core/utilities/structures.py
simu/core/utilities/testing.py
simu/core/utilities/types.py
simu/examples/__init__.py
simu/examples/hello_world.py
simu/examples/ideal_gas.py
simu/examples/ideal_gas_material.py
simu/examples/ideal_gas_param.yml
simu/examples/material_amodel.py
simu/examples/material_factory.py
simu/examples/material_model.py
simu/examples/solver_comparison.py
simu/examples/species_db.yml
simu/examples/thermo_model_structures.yml
simu/examples/tinn.py
sigmamu-0.4.dist-info/METADATA
sigmamu-0.4.dist-info/WHEEL
sigmamu-0.4.dist-info/top_level.txt
sigmamu-0.4.dist-info/RECORD
