Metadata-Version: 2.4
Name: SigmaMu
Version: 0.4
Summary: Equation oriented process modelling library
Home-page: https://github.com/VolkerSiep/SiMu
Author: Volker Siepmann
Author-email: volker.siepmann@gmail.com,
License: LGPL-3.0-or-later
Keywords: thermodynamics,modelling
Classifier: License :: OSI Approved :: GNU Lesser General Public License v3 (LGPLv3)
Classifier: Programming Language :: Python :: 3
Classifier: Topic :: Scientific/Engineering
Classifier: Topic :: Scientific/Engineering :: Chemistry
Requires-Python: >=3.11
License-File: LICENSE
Requires-Dist: pint
Requires-Dist: numpy
Requires-Dist: scipy
Requires-Dist: pypardiso
Requires-Dist: casadi
Requires-Dist: pyyaml
Provides-Extra: dev
Requires-Dist: Sphinx; extra == "dev"
Requires-Dist: sphinxcontrib-bibtex; extra == "dev"
Requires-Dist: sphinx-copybutton; extra == "dev"
Requires-Dist: pytest; extra == "dev"
Requires-Dist: pytest-doctestplus; extra == "dev"
Requires-Dist: matplotlib; extra == "dev"
Requires-Dist: build; extra == "dev"
Requires-Dist: twine; extra == "dev"
Dynamic: license-file
